TRYpros/__init__.py
trypros-2.2.2.dist-info/METADATA
trypros-2.2.2.dist-info/WHEEL
trypros-2.2.2.dist-info/top_level.txt
trypros-2.2.2.dist-info/RECORD
