Metadata-Version: 2.4
Name: TRYpros
Version: 2.2.2
Summary: A collection of useful functions to process data from the TRY Plant Database, supporting a recommended data processing pipeline.
Author-email: Gayathri Girish Nair <girishng@tcd.ie>
Maintainer-email: Gayathri Girish Nair <girishng@tcd.ie>
Requires-Dist: Cartopy
Requires-Dist: global_land_mask
Requires-Dist: matplotlib
Requires-Dist: numpy
Requires-Dist: pandas
Requires-Dist: pyproj
